xlsxtpl/__init__.py
xlsxtpl/writerx.py
xlsxtpl-0.3.1.dist-info/LICENSE
xlsxtpl-0.3.1.dist-info/METADATA
xlsxtpl-0.3.1.dist-info/WHEEL
xlsxtpl-0.3.1.dist-info/top_level.txt
xlsxtpl-0.3.1.dist-info/RECORD
