Metadata-Version: 2.1
Name: xlsxtpl
Version: 0.3.1
Summary: A python module to generate xlsx files from a xlsx template
Home-page: https://github.com/zhangyu836/python-xlsx-template
Author: Zhang Yu
Author-email: zhangyu836@gmail.com
License: MIT
Keywords: xlsx,spreadsheet,workbook,template
Platform: Any platform 
License-File: LICENSE
Requires-Dist: xltpl (>=0.13)
